git_secret/__init__.py
git_secret/_english_words.py
git_secret/files.py
git_secret/filestore.py
git_secret/keystore.py
git_secret/mnemonic.py
git_secret/py.typed
git_secret/script.py
git_secret/utils.py
git_secret_store-0.1.0.dist-info/LICENSE
git_secret_store-0.1.0.dist-info/METADATA
git_secret_store-0.1.0.dist-info/WHEEL
git_secret_store-0.1.0.dist-info/entry_points.txt
git_secret_store-0.1.0.dist-info/top_level.txt
git_secret_store-0.1.0.dist-info/RECORD
